ztick.py
ztick-1.0.0.dist-info/LICENSE.txt
ztick-1.0.0.dist-info/METADATA
ztick-1.0.0.dist-info/WHEEL
ztick-1.0.0.dist-info/top_level.txt
ztick-1.0.0.dist-info/RECORD
