Metadata-Version: 2.1
Name: ztick
Version: 1.0.0
Summary: High-precision smart time delay utility with extreme granularity
Author: M.1XT
License: MIT
Classifier: Programming Language :: Python :: 3
Classifier: Operating System :: OS Independent
Classifier: Intended Audience :: Developers
Classifier: License :: OSI Approved :: MIT License
Requires-Python: >=3.7
License-File: LICENSE.txt
